{
  "hash": "bfeafcbdbcdd910ae60618cca82b604c",
  "result": {
    "engine": "knitr",
    "markdown": "---\ntitle: \"Figures layout\"\ndescription: \"Layout des figures dans les articles avec Quarto.\"\nauthor: \"Marie Gradeler\"\ndate: \"15/10/2024\"\ncategories:\n  - R\n  - tmap\n---\n\n::: {.cell}\n\n:::\n\n\n\n## Test des layouts\n\nClassique, on n’ajoute rien.\n\n\n\n::: {.cell}\n::: {.cell-output-display}\n![](maps_package_files/figure-html/unnamed-chunk-2-1.png){width=672}\n:::\n:::\n\n\n\nOn utilise plus d’espace pour afficher une figure en plus large.\n\n\n\n::: {.cell .column-screen-inset-shaded}\n::: {.cell-output-display}\n![](maps_package_files/figure-html/unnamed-chunk-3-1.png){width=672}\n:::\n:::\n\n\n\nOn peut aussi afficher les figures dans la marge, il semblerait.\n\n\n\n::: {.cell .column-margin}\n::: {.cell-output-display}\n![](maps_package_files/figure-html/unnamed-chunk-4-1.png){width=672}\n:::\n:::\n",
    "supporting": [
      "maps_package_files"
    ],
    "filters": [
      "rmarkdown/pagebreak.lua"
    ],
    "includes": {},
    "engineDependencies": {},
    "preserve": {},
    "postProcess": true
  }
}